<?xml version="1.0" encoding="UTF-8"?>
<objects serializationModel="Studio.01.10.00">
    <object class="Platform" id="{d2df9cb9-281d-47da-b1f1-548de4c385d7}">
        <property name="hardwareType">
            <value>0</value>
        </property>
        <property name="name">
            <value>Desktop</value>
        </property>
        <property name="subDirectory">
            <value>Desktop</value>
        </property>
        <property name="speakerFormat">
            <value>1</value>
        </property>
    </object>
</objects>
